demoparser2-0.39.0.dist-info/METADATA
demoparser2-0.39.0.dist-info/WHEEL
demoparser2/__init__.py
demoparser2/__init__.pyi
demoparser2/demoparser2.cpython-37m-x86_64-linux-gnu.so
demoparser2/py.typed
demoparser2-0.39.0.dist-info/RECORD
