Metadata-Version: 2.4
Name: demoparser2
Version: 0.39.0
Classifier: Programming Language :: Rust
Classifier: Programming Language :: Python :: Implementation :: CPython
Classifier: Programming Language :: Python :: Implementation :: PyPy
Requires-Dist: pandas>=1.5.0
Requires-Dist: numpy
Requires-Dist: polars
Requires-Dist: pyarrow
Requires-Dist: tqdm
Requires-Python: >=3.8
